LICENSE
README.md
setup.py
pyopenetl/__init__.py
pyopenetl/connections.py
pyopenetl/operations.py
pyopenetl/pipelines.py
python_openetl.egg-info/PKG-INFO
python_openetl.egg-info/SOURCES.txt
python_openetl.egg-info/dependency_links.txt
python_openetl.egg-info/requires.txt
python_openetl.egg-info/top_level.txt