Metadata-Version: 2.1
Name: python-openetl
Version: 1.0.15
Summary: A simple python library that makes it easy to create simple ETL pipelines in code.
Home-page: https://github.com/tmccall8829/python-openetl
Author: Tom McCall
Author-email: thomas.e.mccall@gmail.com
License: LICENSE
Platform: UNKNOWN
License-File: LICENSE
